gtts/setup.py
playsound/playsound.py
playsound/setup.py
simplpython/__init__.py
simplpython/simplpython.py
simplpython-0.8.dist-info/METADATA
simplpython-0.8.dist-info/WHEEL
simplpython-0.8.dist-info/top_level.txt
simplpython-0.8.dist-info/RECORD
