Metadata-Version: 2.1
Name: simplpython
Version: 0.8
Summary: SimplPython | The simpler way of Pythoning
Home-page: https://github.com/Samthebest999/simplpython
Author: Samit Mohnot
Author-email: samit.mohnot@gmail.com
License: UNKNOWN
Platform: UNKNOWN
